unfuncaptcha_bda/__init__.py
unfuncaptcha_bda/crypto.py
unfuncaptcha_bda/fingerprint.py
unfuncaptcha_bda-0.0.4.dist-info/LICENSE
unfuncaptcha_bda-0.0.4.dist-info/METADATA
unfuncaptcha_bda-0.0.4.dist-info/WHEEL
unfuncaptcha_bda-0.0.4.dist-info/top_level.txt
unfuncaptcha_bda-0.0.4.dist-info/RECORD
