Metadata-Version: 2.1
Name: unfuncaptcha_bda
Version: 0.0.4
Summary: View, edit, and repackage Arkose Labs Funcaptcha fingerprints
Author-email: bc <no@dont.email.me>
Project-URL: Homepage, https://github.com/unfuncaptcha/bda
Project-URL: Issues, https://github.com/unfuncaptcha/bda/issues
Classifier: Programming Language :: Python :: 3
Classifier: License :: OSI Approved :: MIT License
Classifier: Operating System :: OS Independent
Requires-Python: >=3.8
License-File: LICENSE
